django_mitre/__init__.py
django_mitre/attack/__init__.py
django_mitre/attack/apps.py
django_mitre/attack/filters.py
django_mitre/attack/forms.py
django_mitre/attack/models.py
django_mitre/attack/patterns.py
django_mitre/attack/urls.py
django_mitre/attack/utils.py
django_mitre/attack/views.py
django_mitre/attack/management/__init__.py
django_mitre/attack/management/commands/__init__.py
django_mitre/attack/management/commands/ingest_attack_data.py
django_mitre/attack/migrations/0001_initial.py
django_mitre/attack/migrations/0002_auto_20221218_0047.py
django_mitre/attack/migrations/0003_data_migration.py
django_mitre/attack/migrations/0004_campaign.py
django_mitre/attack/migrations/0005_auto_20240606_0143.py
django_mitre/attack/migrations/__init__.py
django_mitre/attack/static/mitreattack/main.css
django_mitre/attack/static/mitreattack/main.js
django_mitre/attack/templates/mitreattack/display_mitre_data_component_references.html
django_mitre/attack/templates/mitreattack/display_mitre_references_by_type.html
django_mitre/attack/templates/mitreattack/display_mitre_tactic_techniques.html
django_mitre/attack/templates/mitreattack/display_mitre_target_detects_references.html
django_mitre/attack/templates/mitreattack/list_techniques_for_tactic.html
django_mitre/attack/templates/mitreattack/campaign/detail.html
django_mitre/attack/templates/mitreattack/datacomponent/detail.html
django_mitre/attack/templates/mitreattack/datasource/detail.html
django_mitre/attack/templates/mitreattack/group/detail.html
django_mitre/attack/templates/mitreattack/matrix/detail.html
django_mitre/attack/templates/mitreattack/matrix/index.html
django_mitre/attack/templates/mitreattack/mitigation/detail.html
django_mitre/attack/templates/mitreattack/software/detail.html
django_mitre/attack/templates/mitreattack/tactic/detail.html
django_mitre/attack/templates/mitreattack/technique/detail.html
django_mitre/attack/templatetags/__init__.py
django_mitre/attack/templatetags/mitreattack_tags.py
django_mitre-0.2.1.dist-info/METADATA
django_mitre-0.2.1.dist-info/WHEEL
django_mitre-0.2.1.dist-info/licenses/LICENSE
django_mitre-0.2.1.dist-info/RECORD
