Metadata-Version: 2.4
Name: django-mitre
Version: 0.2.1
Summary: MITRE ATT&CK and MBC ingesters, models, and views
Project-URL: Homepage, https://github.com/The-Shadowserver-Foundation/django-mitre
Project-URL: Issues, https://github.com/The-Shadowserver-Foundation/django-mitre/issues
Author: The Shadowserver Foundation
Author-email: Michael Mulich <michael@mulich.com>
License-Expression: GPL-3.0
License-File: LICENSE
Classifier: Framework :: Django
Classifier: Framework :: Django :: 4
Classifier: Framework :: Django :: 5
Classifier: Operating System :: OS Independent
Classifier: Programming Language :: Python :: 3
Requires-Python: >=3.10
Requires-Dist: django-filtering-ui>=0.0.8
Requires-Dist: django-filtering>=0.3.2
Requires-Dist: django>=4.2
Requires-Dist: markdown
Requires-Dist: pygithub
Provides-Extra: django42
Requires-Dist: django-querystring-tag; extra == 'django42'
Provides-Extra: test
Requires-Dist: model-bakery; extra == 'test'
Provides-Extra: tests
Requires-Dist: model-bakery; extra == 'tests'
